pyscicat/__init__.py
pyscicat/_version.py
pyscicat/client.py
pyscicat/model.py
pyscicat/hdf5/__init__.py
pyscicat/hdf5/h5tools.py
pyscicat/hdf5/scientific_metadata.py
pyscicat/ingest/__init__.py
pyscicat-0.4.8.dist-info/METADATA
pyscicat-0.4.8.dist-info/WHEEL
pyscicat-0.4.8.dist-info/licenses/AUTHORS.rst
pyscicat-0.4.8.dist-info/licenses/LICENSE
pyscicat-0.4.8.dist-info/licenses/LICENSE.txt
pyscicat-0.4.8.dist-info/RECORD
