Metadata-Version: 2.4
Name: pyscicat
Version: 0.4.8
Summary: a python API to communicate with the Scicat API
Project-URL: Homepage, https://github.com/scicatproject/pyscicat
Author-email: Scicat Project Contributors <dmcreynolds@lbl.gov>
Maintainer-email: Scicat Project Team <dmcreynolds@lbl.gov>
License-File: AUTHORS.rst
License-File: LICENSE
License-File: LICENSE.txt
Classifier: Development Status :: 2 - Pre-Alpha
Classifier: Natural Language :: English
Classifier: Programming Language :: Python :: 3.7
Requires-Python: >=3.9
Requires-Dist: pydantic
Requires-Dist: requests
Provides-Extra: dev
Requires-Dist: black; extra == 'dev'
Requires-Dist: codecov; extra == 'dev'
Requires-Dist: coverage; extra == 'dev'
Requires-Dist: flake8; extra == 'dev'
Requires-Dist: isort; extra == 'dev'
Requires-Dist: mypy; extra == 'dev'
Requires-Dist: pytest; extra == 'dev'
Requires-Dist: requests-mock; extra == 'dev'
Requires-Dist: sphinx; extra == 'dev'
Requires-Dist: twine; extra == 'dev'
Requires-Dist: types-requests; extra == 'dev'
Provides-Extra: docs
Requires-Dist: ipython; extra == 'docs'
Requires-Dist: matplotlib; extra == 'docs'
Requires-Dist: mistune<2.0.0; extra == 'docs'
Requires-Dist: myst-parser; extra == 'docs'
Requires-Dist: numpydoc; extra == 'docs'
Requires-Dist: sphinx-click; extra == 'docs'
Requires-Dist: sphinx-copybutton; extra == 'docs'
Requires-Dist: sphinx-rtd-theme; extra == 'docs'
Requires-Dist: sphinxcontrib-openapi; extra == 'docs'
Provides-Extra: hdf5
Requires-Dist: h5py; extra == 'hdf5'
Requires-Dist: hdf5plugin; extra == 'hdf5'
